{"girlName":"上条るい","eventName":"あの頃は…","rarity":"UR","attribute":"COOL","isExed":true,"attack":32744,"defence":27698,"cost":23,"skillLevel":15,"skillType":"COOLの主ｾﾝﾊﾞﾂ全員&副ｾﾝﾊﾞﾂ1人の攻援ｽｰﾊﾟｰ特大UP"}
{"girlName":"朝比奈桃子","eventName":"しっぽﾌﾘﾌﾘ","rarity":"UR","attribute":"SWEET","isExed":false,"attack":31918,"defence":28098,"cost":24,"skillLevel":14,"skillType":"SWEETの主ｾﾝﾊﾞﾂ全員&副ｾﾝﾊﾞﾂ1人の攻援ｽｰﾊﾟｰ特大UP"}
{"girlName":"真白透子","eventName":"特別な想い","rarity":"SSR","attribute":"COOL","isExed":true,"attack":31655,"defence":25688,"cost":24,"skillLevel":14,"skillType":"COOLの主ｾﾝﾊﾞﾂ全員&副ｾﾝﾊﾞﾂ1人の攻援特大UP"}
{"girlName":"鈴河凜乃","eventName":"窮猫鼠噛み","rarity":"SSR","attribute":"POP","isExed":true,"attack":31655,"defence":25688,"cost":24,"skillLevel":10,"skillType":"POPの主ｾﾝﾊﾞﾂ全員&副ｾﾝﾊﾞﾂ1人の攻援特大UP"}